setup.py
agottani_distributions/Binomialdistribution.py
agottani_distributions/Gaussiandistribution.py
agottani_distributions/Generaldistribution.py
agottani_distributions/__init__.py
agottani_distributions.egg-info/PKG-INFO
agottani_distributions.egg-info/SOURCES.txt
agottani_distributions.egg-info/dependency_links.txt
agottani_distributions.egg-info/not-zip-safe
agottani_distributions.egg-info/top_level.txt