Metadata-Version: 1.0
Name: agottani-distributions
Version: 1.4
Summary: Gaussian and binomial distributions
Home-page: UNKNOWN
Author: Luis Fernando Rodrigues Agottani
Author-email: luisfernandoengmec@gmail.com
License: UNKNOWN
Platform: UNKNOWN
